shelcolors_ansi/__init__.py
shelcolors_ansi/ansi.py
shelcolors_ansi-0.1.7.dist-info/METADATA
shelcolors_ansi-0.1.7.dist-info/WHEEL
shelcolors_ansi-0.1.7.dist-info/top_level.txt
shelcolors_ansi-0.1.7.dist-info/RECORD
