Metadata-Version: 2.4
Name: shelcolors.ansi
Version: 0.1.7
Summary: ANSI color helper
Author: Sheldon
Requires-Python: >=3.8
